deslib/__init__.py
deslib/base.py
deslib/dcs/__init__.py
deslib/dcs/a_posteriori.py
deslib/dcs/a_priori.py
deslib/dcs/base.py
deslib/dcs/lca.py
deslib/dcs/mcb.py
deslib/dcs/mla.py
deslib/dcs/ola.py
deslib/dcs/rank.py
deslib/des/__init__.py
deslib/des/base.py
deslib/des/des_clustering.py
deslib/des/des_knn.py
deslib/des/des_mi.py
deslib/des/des_p.py
deslib/des/knop.py
deslib/des/knora_e.py
deslib/des/knora_u.py
deslib/des/meta_des.py
deslib/des/probabilistic/__init__.py
deslib/des/probabilistic/base.py
deslib/des/probabilistic/deskl.py
deslib/des/probabilistic/exponential.py
deslib/des/probabilistic/logarithmic.py
deslib/des/probabilistic/minimum_difference.py
deslib/des/probabilistic/rrc.py
deslib/static/__init__.py
deslib/static/base.py
deslib/static/oracle.py
deslib/static/single_best.py
deslib/static/stacked.py
deslib/static/static_selection.py
deslib/tests/__init__.py
deslib/tests/conftest.py
deslib/tests/test_base.py
deslib/tests/test_des_integration.py
deslib/tests/test_des_integration_multiclass.py
deslib/tests/test_integration_DFP_IH.py
deslib/tests/test_integration_dfp.py
deslib/tests/test_metric.py
deslib/tests/dcs/__init__.py
deslib/tests/dcs/test_a_posteriori.py
deslib/tests/dcs/test_a_priori.py
deslib/tests/dcs/test_base.py
deslib/tests/dcs/test_lca.py
deslib/tests/dcs/test_mcb.py
deslib/tests/dcs/test_mla.py
deslib/tests/dcs/test_ola.py
deslib/tests/dcs/test_rank.py
deslib/tests/des/__init__.py
deslib/tests/des/test_base.py
deslib/tests/des/test_des_clustering.py
deslib/tests/des/test_des_knn.py
deslib/tests/des/test_des_mi.py
deslib/tests/des/test_desp.py
deslib/tests/des/test_knop.py
deslib/tests/des/test_knorae.py
deslib/tests/des/test_knorau.py
deslib/tests/des/test_meta_des.py
deslib/tests/des/test_probabilistic.py
deslib/tests/static/__init__.py
deslib/tests/static/test_oracle.py
deslib/tests/static/test_single_best.py
deslib/tests/static/test_stacked.py
deslib/tests/static/test_static_selection.py
deslib/tests/util/__init__.py
DESlib-0.3.7.dist-info/LICENSE.txt
DESlib-0.3.7.dist-info/METADATA
DESlib-0.3.7.dist-info/WHEEL
DESlib-0.3.7.dist-info/top_level.txt
DESlib-0.3.7.dist-info/RECORD
