Metadata-Version: 2.1
Name: DESlib
Version: 0.3.7
Summary: Implementation of Dynamic Ensemble Selection methods
Home-page: https://github.com/Menelau/DESlib
Author: Rafael M. O. Cruz
Author-email: rafaelmenelau@gmail.com
Maintainer: Rafael M. O. Cruz, L. G. Hafemann
Maintainer-email: rafaelmenelau@gmail.com
License: BSD 3-clause "New" or "Revised License"
Classifier: Development Status :: 3 - Alpha
Classifier: Intended Audience :: Developers
Classifier: Intended Audience :: Science/Research
Classifier: License :: OSI Approved :: BSD License
Classifier: Programming Language :: Python :: 3
Classifier: Programming Language :: Python :: 3.5
Classifier: Programming Language :: Python :: 3.6
Classifier: Programming Language :: Python :: 3.7
Classifier: Programming Language :: Python :: 3.8
Classifier: Programming Language :: Python :: 3.9
Classifier: Programming Language :: Python :: 3.10
Classifier: Programming Language :: Python :: 3.11
Classifier: Programming Language :: Python :: 3.12
Classifier: Topic :: Scientific/Engineering :: Artificial Intelligence
Requires-Python: >=3
License-File: LICENSE.txt
Requires-Dist: scikit-learn >=1.0.2
Requires-Dist: numpy >=1.17.0
Requires-Dist: scipy >=1.4.0
